ledger/__init__.py
ledger/blue.py
ledger/btc.py
ledger/eth.py
ledger/ledger_types.py
ledger/py.typed
ledger/utils.py
riemann_ledger-2.2.1.dist-info/LICENSE-APACHE2.md
riemann_ledger-2.2.1.dist-info/LICENSE-MIT.md
riemann_ledger-2.2.1.dist-info/METADATA
riemann_ledger-2.2.1.dist-info/WHEEL
riemann_ledger-2.2.1.dist-info/top_level.txt
riemann_ledger-2.2.1.dist-info/RECORD
