Metadata-Version: 2.1
Name: riemann-ledger
Version: 2.2.1
Summary: Sign Bitcoin and Ethereum transactions on your Ledger
Home-page: https://github.com/summa-tx/riemann-ledger
Author: ['James Prestwich']
Author-email: james@summa.one
License: MIT OR Apache-2.0
Platform: UNKNOWN
Requires-Python: >=3.7
Requires-Dist: ledgerblue (==0.1.23)
Requires-Dist: riemann-tx (==2.1.0)
Requires-Dist: riemann-ether (==4.2.1)
Requires-Dist: mypy-extensions
